{
	"configurations" : 
	[
		{
			"directories" : 
			[
				{
					"build" : ".",
					"jsonFile" : "directory-.-Debug-d0094a50bb2071803777.json",
					"minimumCMakeVersion" : 
					{
						"string" : "3.25"
					},
					"projectIndex" : 0,
					"source" : ".",
					"targetIndexes" : 
					[
						0
					]
				}
			],
			"name" : "Debug",
			"projects" : 
			[
				{
					"directoryIndexes" : 
					[
						0
					],
					"name" : "LinkedQueue",
					"targetIndexes" : 
					[
						0
					]
				}
			],
			"targets" : 
			[
				{
					"directoryIndex" : 0,
					"id" : "LinkedQueue::@6890427a1f51a3e7e1df",
					"jsonFile" : "target-LinkedQueue-Debug-c272c6db0afecd0de455.json",
					"name" : "LinkedQueue",
					"projectIndex" : 0
				}
			]
		}
	],
	"kind" : "codemodel",
	"paths" : 
	{
		"build" : "D:/Data Structures/LinkedQueue/cmake-build-debug",
		"source" : "D:/Data Structures/LinkedQueue"
	},
	"version" : 
	{
		"major" : 2,
		"minor" : 4
	}
}
